README.md
setup.cfg
setup.py
orthorectification/__init__.py
orthorectification/experimental.py
orthorectification/io_tools.py
orthorectification/ortho_tools.py
orthorectification/scaling_tools.py
orthorectification/visualization_tools.py
orthorectification.egg-info/PKG-INFO
orthorectification.egg-info/SOURCES.txt
orthorectification.egg-info/dependency_links.txt
orthorectification.egg-info/requires.txt
orthorectification.egg-info/top_level.txt
orthorectification.egg-info/zip-safe