Metadata-Version: 2.1
Name: orthorectification
Version: 0.0.4
Summary: UNKNOWN
Home-page: https://github.com/mpfaffenberger/orthorectification
Author: Michael Pfaffenberger
Author-email: mike.pfaffenberger@gmail.com
License: UNKNOWN
Download-URL: https://github.com/mpfaffenberger/orthorectification/archive/orthorectification-0.0.3.tar.gz
Platform: MacOS X
Platform: Linux
Classifier: Programming Language :: Python :: 3
Classifier: Programming Language :: Python :: 3.6
Classifier: Programming Language :: Python :: 3.7
Classifier: Programming Language :: Python :: 3.8
Classifier: Operating System :: POSIX :: Linux
Classifier: Operating System :: MacOS :: MacOS X
Classifier: Topic :: Utilities
Classifier: Typing :: Typed
